sainpse/__init__.py
sainpse/finance/data/TwelveData.py
sainpse-0.2.3.dist-info/LICENSE
sainpse-0.2.3.dist-info/WHEEL
sainpse-0.2.3.dist-info/METADATA
sainpse-0.2.3.dist-info/RECORD
