Metadata-Version: 2.1
Name: sainpse
Version: 0.2.3
Summary: The Sainpse Institute Utility Python Packages - Bugfixes
Author: Marcus Madumo
Author-email: marcusm@sainpse.com
Requires-Python: >=3.8,<4.0
Classifier: Programming Language :: Python :: 3
Classifier: Programming Language :: Python :: 3.10
Classifier: Programming Language :: Python :: 3.8
Classifier: Programming Language :: Python :: 3.9
Requires-Dist: pendulum (>=2.1.2,<3.0.0)
Requires-Dist: twelvedata (>=1.2.4,<2.0.0)
